RedisQueue/__init__.py
RedisQueue/multi_process.py
RedisQueue/redis_connector.py
RedisQueue/exception/__init__.py
RedisQueue/exception/local_exceptions.py
RedisQueueDemo/__init__.py
RedisQueueDemo/demo.py
RedisQueueDemo/test_abc.py
demo/__init__.py
demo/demo.py
demo/test_abc.py
run/__init__.py
run/multi_process.py
run/redis_connector.py
run/exception/__init__.py
run/exception/local_exceptions.py
zzha529_test-1.16.dist-info/METADATA
zzha529_test-1.16.dist-info/WHEEL
zzha529_test-1.16.dist-info/top_level.txt
zzha529_test-1.16.dist-info/RECORD
