Metadata-Version: 2.1
Name: zzha529-test
Version: 1.16
Summary: personal redis queue consumer
Author: zzha529
License: UNKNOWN
Platform: UNKNOWN
Requires-Python: >3
Requires-Dist: redis (==4.1.0)
